Metadata-Version: 1.0
Name: lonnberg-svensson2017
Version: 1.0.0
Summary: Expression data for Lönnberg + Svensson et al, "Single-cell RNA-seq and computational analysis using temporal mixture modelling resolves Th1/Tfh fate bifurcation in malaria," Science Immunology (2017)
Home-page: https://github.com/olgabot/lonnberg_svensson2017
Author: Olga Botvinnik
Author-email: olga.botvinnik@gmail.com
License: MIT
Platform: UNKNOWN
